richit/__init__.py
richit/__main__.py
richit/panel.py
richit-0.2.0.dist-info/METADATA
richit-0.2.0.dist-info/WHEEL
richit-0.2.0.dist-info/top_level.txt
richit-0.2.0.dist-info/RECORD
